fw_gear_img_to_dicom/__init__.py
fw_gear_img_to_dicom/convert_img_to_dcm.py
fw_gear_img_to_dicom/main.py
fw_gear_img_to_dicom/parser.py
fw_gear_img_to_dicom-0.1.1.dist-info/LICENSE
fw_gear_img_to_dicom-0.1.1.dist-info/METADATA
fw_gear_img_to_dicom-0.1.1.dist-info/WHEEL
fw_gear_img_to_dicom-0.1.1.dist-info/RECORD
